biodatatools/__init__.py
biodatatools/utils/__init__.py
biodatatools/utils/alignment.py
biodatatools/utils/common.py
biodatatools/utils/geneannotation.py
biodatatools/utils/genomic.py
biodatatools/utils/sequence.py
biodatatools-0.0.9.dist-info/METADATA
biodatatools-0.0.9.dist-info/WHEEL
biodatatools-0.0.9.dist-info/entry_points.txt
biodatatools-0.0.9.dist-info/top_level.txt
biodatatools-0.0.9.dist-info/RECORD
