Metadata-Version: 2.1
Name: biodatatools
Version: 0.0.9
Summary: A python package with useful biological data processing methods
Home-page: https://github.com/aldenleung/biodatatools/
Author: Alden Leung
Author-email: alden.leung@gmail.com
Classifier: Programming Language :: Python :: 3.7
Classifier: Programming Language :: Python :: 3.8
Classifier: Programming Language :: Python :: 3.9
Classifier: Programming Language :: Python :: 3.10
Classifier: Programming Language :: Python :: 3.11
Classifier: License :: OSI Approved :: GNU General Public License v3 (GPLv3)
Requires-Dist: genomictools>=0.0.8
Requires-Dist: biodata>=0.1.5
Requires-Dist: biodataplot>=0.0.4
Requires-Dist: simplevc>=0.0.3
Requires-Dist: commonhelper>=0.0.5
Requires-Dist: mphelper>=0.0.3
Requires-Dist: pysam>=0.22.1
Requires-Dist: pyBigWig>=0.3.22
Requires-Dist: numpy>=1.26.4
Requires-Dist: scipy>=1.13.1
Requires-Dist: pandas>=2.2.2
